LICENSE
MANIFEST.in
README.rst
setup.py
shout.py
pyshout.egg-info/PKG-INFO
pyshout.egg-info/SOURCES.txt
pyshout.egg-info/dependency_links.txt
pyshout.egg-info/top_level.txt