Metadata-Version: 1.1
Name: pyshout
Version: 0.2.3
Summary: Loud python messaging!
Home-page: http://github.com/danbradham/shout
Author: Dan Bradham
Author-email: danieldbradham@gmail.com
License: MIT
Platform: UNKNOWN
Classifier: Development Status :: 3 - Alpha
Classifier: Intended Audience :: Developers
Classifier: License :: OSI Approved :: MIT License
Classifier: Natural Language :: English
Classifier: Operating System :: OS Independent
Classifier: Programming Language :: Python
Classifier: Programming Language :: Python :: 2
Classifier: Programming Language :: Python :: 3
Classifier: Topic :: Software Development :: Libraries :: Python Modules
